src/__init__.py
src/api/__init__.py
src/api/base.py
src/api/constants.py
src/api/sql/__init__.py
src/api/sql/base.py
src/api/sql/analytical/__init__.py
src/api/sql/analytical/base.py
src/api/sql/transactional/__init__.py
src/api/sql/transactional/base.py
src/api/utils/__init__.py
src/api/utils/base.py
src/api/utils/stringify/__init__.py
src/api/utils/stringify/base.py
data_solutions_python_sdk-0.0.1.dist-info/LICENCE
data_solutions_python_sdk-0.0.1.dist-info/METADATA
data_solutions_python_sdk-0.0.1.dist-info/WHEEL
data_solutions_python_sdk-0.0.1.dist-info/top_level.txt
data_solutions_python_sdk-0.0.1.dist-info/RECORD
