Metadata-Version: 2.1
Name: data_solutions_python_sdk
Version: 0.0.1
Summary: Web3 Data Made Simple. Powerful APIs for accessing human-readable blockchain data at scale: from blocks and transactions to NFTs and tokens.
Home-page: https://github.com/TransposeData/chainalysis-data-solutions-python-sdk
Author: Rah Tarar (musa-tarar)
Author-email: musa.nishat@chainalysis.com
License: MIT
Keywords: web3,data,ethereum,web3 data,ethereum data
Classifier: Development Status :: 3 - Alpha
Classifier: Intended Audience :: Developers
Classifier: Intended Audience :: Information Technology
Classifier: License :: OSI Approved :: MIT License
Classifier: Natural Language :: English
Classifier: Topic :: Database
Classifier: Topic :: Utilities
License-File: LICENCE
Requires-Dist: requests
Requires-Dist: pandas
Requires-Dist: python-dotenv
